{"coins":{"0xBitcoin":{"id":315,"tag":"0xBTC","algorithm":"SHA3Solidity","lagging":true,"listed":true,"status":"Active","testing":false},"365Coin":{"id":74,"tag":"365","algorithm":"Keccak","lagging":true,"listed":false,"status":"No available stats","testing":false},"Aced":{"id":268,"tag":"ACED","algorithm":"X16S","lagging":false,"listed":false,"status":"PoW phase over","testing":false},"Actinium":{"id":290,"tag":"ACM","algorithm":"Lyra2z","lagging":false,"listed":true,"status":"Active","testing":false},"Aiden":{"id":65,"tag":"ADN","algorithm":"Scrypt-OG","lagging":true,"listed":false,"status":"No available stats","testing":false},"Adzcoin":{"id":157,"tag":"ADZ","algorithm":"X11","lagging":true,"listed":false,"status":"No available stats","testing":false},"Aeternity":{"id":297,"tag":"AE","algorithm":"CuckooCycle","lagging":false,"listed":true,"status":"Active","testing":false},"Aeon":{"id":192,"tag":"AEON","algorithm":"K12","lagging":false,"listed":true,"status":"Active","testing":false},"Argoneum":{"id":285,"tag":"AGM","algorithm":"PHI2","lagging":false,"listed":false,"status":"Active","testing":false},"Aion":{"id":272,"tag":"AION","algorithm":"Equihash (210,9)","lagging":false,"listed":true,"status":"Active","testing":false},"Ambercoin":{"id":133,"tag":"AMBER","algorithm":"X13","lagging":true,"listed":false,"status":"No available stats","testing":false},"Amsterdamcoin":{"id":145,"tag":"AMS","algorithm":"Quark","lagging":true,"listed":false,"status":"No available stats","testing":false},"Anon":{"id":276,"tag":"ANON","algorithm":"EquihashZero","lagging":true,"listed":false,"status":"No available stats","testing":false},"ARG-SHA":{"id":170,"tag":"ARG","algorithm":"SHA-256","lagging":true,"listed":false,"status":"Inactive","testing":false},"ARG-Scrypt":{"id":158,"tag":"ARG","algorithm":"Scrypt","lagging":true,"listed":false,"status":"Inactive","testing":false},"Aricoin":{"id":110,"tag":"ARI","algorithm":"Scrypt","lagging":true,"listed":false,"status":"No available stats","testing":false},"Pirate":{"id":298,"tag":"ARRR","algorithm":"Equihash","lagging":false,"listed":true,"status":"Active","testing":false},"AUR-SHA":{"id":228,"tag":"AUR","algorithm":"SHA-256","lagging":false,"listed":false,"status":"Active","testing":false},"AUR-Scrypt":{"id":40,"tag":"AUR","algorithm":"Scrypt","lagging":false,"listed":false,"status":"Active","testing":false},"Axe":{"id":313,"tag":"AXE","algorithm":"X11","lagging":false,"listed":true,"status":"Active","testing":false},"Azart":{"id":281,"tag":"AZART","algorithm":"X17","lagging":true,"listed":false,"status":"No available stats","testing":false},"BitcoinDiamond":{"id":278,"tag":"BCD","algorithm":"BCD","lagging":false,"listed":true,"status":"Active","testing":false},"BitcoinCash":{"id":193,"tag":"BCH","algorithm":"SHA-256","lagging":false,"listed":true,"status":"Active","testing":false},"Bitcoin Interest":{"id":245,"tag":"BCI","algorithm":"ProgPow","lagging":false,"listed":false,"status":"Active","testing":false},"Bytecoin":{"id":103,"tag":"BCN","algorithm":"CryptoNight","lagging":false,"listed":true,"status":"Active","testing":false},"Beam":{"id":294,"tag":"BEAM","algorithm":"BeamHashIII","lagging":false,"listed":true,"status":"Active","testing":false},"Belacoin":{"id":182,"tag":"BELA","algorithm":"Scrypt","lagging":true,"listed":false,"status":"No market","testing":false},"Bipcoin":{"id":171,"tag":"BIP","algorithm":"CryptoNight","lagging":true,"listed":false,"status":"No available stats","testing":false},"Bismuth":{"id":232,"tag":"BIS","algorithm":"SHA-224","lagging":false,"listed":false,"status":"Active","testing":false},"BitCash":{"id":304,"tag":"BITC","algorithm":"X25X","lagging":false,"listed":true,"status":"Active","testing":false},"Bloc":{"id":312,"tag":"BLOC","algorithm":"CryptoNightHaven","lagging":false,"listed":true,"status":"Active","testing":false},"Dobbscoin":{"id":131,"tag":"BOB","algorithm":"Scrypt","lagging":true,"listed":false,"status":"No available stats","testing":false},"BitSend":{"id":201,"tag":"BSD","algorithm":"Xevan","lagging":false,"listed":false,"status":"Active","testing":false},"BlockStamp":{"id":314,"tag":"BST","algorithm":"BlockStamp","lagging":true,"listed":false,"status":"No available stats","testing":false},"GlobalBoost-Y":{"id":138,"tag":"BSTY","algorithm":"Yescrypt","lagging":true,"listed":false,"status":"No available stats","testing":false},"BitcoinSV":{"id":289,"tag":"BSV","algorithm":"SHA-256","lagging":false,"listed":true,"status":"Active","testing":false},"Bata":{"id":144,"tag":"BTA","algorithm":"Scrypt","lagging":false,"listed":false,"status":"No available stats","testing":false},"Bitcoin":{"id":1,"tag":"BTC","algorithm":"SHA-256","lagging":false,"listed":true,"status":"Active","testing":false},"BitcoinPrivate":{"id":230,"tag":"BTCP","algorithm":"EquihashZero","lagging":true,"listed":true,"status":"Mining paused","testing":false},"BitcoinZ":{"id":207,"tag":"BTCZ","algorithm":"Zhash","lagging":false,"listed":false,"status":"Active","testing":false},"BitcoinGold":{"id":214,"tag":"BTG","algorithm":"Zhash","lagging":false,"listed":true,"status":"Active","testing":false},"Bytom":{"id":242,"tag":"BTM","algorithm":"Tensority","lagging":false,"listed":true,"status":"Active","testing":false},"Bitmark":{"id":111,"tag":"BTM","algorithm":"Scrypt","lagging":true,"listed":false,"status":"No available stats","testing":false},"Bitcore":{"id":202,"tag":"BTX","algorithm":"Mega-BTX","lagging":false,"listed":false,"status":"Active","testing":false},"Burnercoin":{"id":90,"tag":"BURN","algorithm":"X13","lagging":true,"listed":false,"status":"PoW phase over","testing":false},"Bulwark":{"id":224,"tag":"BWK","algorithm":"NIST5","lagging":false,"listed":false,"status":"PoW phase over","testing":false},"Cachecoin":{"id":97,"tag":"CACH","algorithm":"Chacha (Nf18)","lagging":true,"listed":false,"status":"No available stats","testing":false},"Cannabiscoin":{"id":188,"tag":"CANN","algorithm":"X11","lagging":false,"listed":false,"status":"Active","testing":false},"BottleCaps":{"id":120,"tag":"CAP","algorithm":"Scrypt","lagging":true,"listed":false,"status":"No available stats","testing":false},"Litecash":{"id":326,"tag":"CASH","algorithm":"Equihash (150,5)","lagging":false,"listed":false,"status":"Active","testing":false},"Catcoin":{"id":198,"tag":"CAT","algorithm":"Scrypt","lagging":true,"listed":false,"status":"No available stats","testing":false},"Bullion":{"id":126,"tag":"CBX","algorithm":"Scrypt","lagging":true,"listed":false,"status":"PoW phase over","testing":false},"Conceal":{"id":305,"tag":"CCX","algorithm":"CryptoNightGPU","lagging":false,"listed":true,"status":"Active","testing":false},"Conflux":{"id":337,"tag":"CFX","algorithm":"Octopus","lagging":false,"listed":true,"status":"Active","testing":false},"X-Children":{"id":116,"tag":"CHILD","algorithm":"X11","lagging":true,"listed":false,"status":"No available stats","testing":false},"Nervos":{"id":321,"tag":"CKB","algorithm":"Eaglesong","lagging":false,"listed":true,"status":"Active","testing":false},"Checkcoin":{"id":123,"tag":"CKC","algorithm":"X11","lagging":true,"listed":false,"status":"No available stats","testing":false},"Callisto":{"id":283,"tag":"CLO","algorithm":"Ethash","lagging":false,"listed":true,"status":"Active","testing":false},"Cloakcoin":{"id":88,"tag":"CLOAK","algorithm":"X13","lagging":true,"listed":false,"status":"PoW phase over","testing":false},"Commercium":{"id":255,"tag":"CMM","algorithm":"Equihash","lagging":false,"listed":false,"status":"Active","testing":false},"CRowdCLassic":{"id":226,"tag":"CRCL","algorithm":"NeoScrypt","lagging":true,"listed":false,"status":"No available stats","testing":false},"Creativecoin":{"id":199,"tag":"CREA","algorithm":"Keccak-C","lagging":false,"listed":false,"status":"PoW phase over","testing":false},"Creamcoin":{"id":206,"tag":"CRM","algorithm":"Skein","lagging":true,"listed":false,"status":"Active","testing":false},"CrocodileCash":{"id":208,"tag":"CROC","algorithm":"SHA-256","lagging":true,"listed":false,"status":"No available stats","testing":false},"Crown":{"id":165,"tag":"CRW","algorithm":"SHA-256","lagging":false,"listed":false,"status":"PoW phase over","testing":false},"Cryptcoin":{"id":86,"tag":"CRYPT","algorithm":"X11","lagging":true,"listed":false,"status":"PoW phase over","testing":false},"Crypto":{"id":134,"tag":"CTO","algorithm":"Lyra2RE","lagging":true,"listed":false,"status":"No available stats","testing":false},"Cortex":{"id":329,"tag":"CTXC","algorithm":"CuckooCycleCortex","lagging":false,"listed":false,"status":"Active","testing":false},"Curecoin":{"id":76,"tag":"CURE","algorithm":"SHA-256","lagging":true,"listed":false,"status":"No available stats","testing":false},"Denarius":{"id":187,"tag":"D","algorithm":"Tribus","lagging":false,"listed":true,"status":"Active","testing":false},"Dash":{"id":34,"tag":"DASH","algorithm":"X11","lagging":false,"listed":true,"status":"Active","testing":false},"Dubaicoin":{"id":271,"tag":"DBIX","algorithm":"Ethash","lagging":false,"listed":true,"status":"Active","testing":false},"Decred":{"id":152,"tag":"DCR","algorithm":"Blake (14r)","lagging":false,"listed":true,"status":"Active","testing":false},"Dinastycoin":{"id":227,"tag":"DCY","algorithm":"RandomX","lagging":true,"listed":false,"status":"No available stats","testing":false},"Deutsche eMark":{"id":180,"tag":"DEM","algorithm":"SHA-256","lagging":false,"listed":false,"status":"Active","testing":false},"Dero":{"id":291,"tag":"DERO","algorithm":"AstroBWT","lagging":false,"listed":false,"status":"Active","testing":false},"DGB-Scrypt":{"id":28,"tag":"DGB","algorithm":"Scrypt","lagging":false,"listed":true,"status":"Active","testing":false},"DGB-Qubit":{"id":115,"tag":"DGB","algorithm":"Qubit","lagging":false,"listed":true,"status":"Active","testing":false},"DGB-Skein":{"id":114,"tag":"DGB","algorithm":"Skein","lagging":false,"listed":true,"status":"Active","testing":false},"DGB-Odocrypt":{"id":112,"tag":"DGB","algorithm":"Odocrypt","lagging":false,"listed":true,"status":"Active","testing":false},"DGB-SHA":{"id":113,"tag":"DGB","algorithm":"SHA-256","lagging":false,"listed":true,"status":"Active","testing":false},"DGC-X11":{"id":125,"tag":"DGC","algorithm":"X11","lagging":true,"listed":false,"status":"No available stats","testing":false},"DGC-Scrypt":{"id":27,"tag":"DGC","algorithm":"Scrypt","lagging":true,"listed":false,"status":"No available stats","testing":false},"DGC-SHA":{"id":124,"tag":"DGC","algorithm":"SHA-256","lagging":true,"listed":false,"status":"No available stats","testing":false},"Dinero":{"id":236,"tag":"DIN","algorithm":"NeoScrypt","lagging":true,"listed":false,"status":"No available stats","testing":false},"Diamond":{"id":43,"tag":"DMD","algorithm":"Groestl","lagging":false,"listed":false,"status":"PoW phase over","testing":false},"Darknet":{"id":153,"tag":"DNET","algorithm":"Quark","lagging":true,"listed":false,"status":"PoW phase over","testing":false},"Dogecoin":{"id":6,"tag":"DOGE","algorithm":"Scrypt","lagging":false,"listed":true,"status":"Active","testing":false},"DopeCoin":{"id":61,"tag":"DOPE","algorithm":"Scrypt","lagging":true,"listed":false,"status":"No market","testing":false},"DigitalpriceClassic":{"id":183,"tag":"DPC","algorithm":"X11","lagging":true,"listed":false,"status":"Inactive","testing":false},"Dashcoin":{"id":129,"tag":"DSH","algorithm":"CryptoNight","lagging":false,"listed":false,"status":"No available stats","testing":false},"Parallel-SHA":{"id":141,"tag":"DUO","algorithm":"SHA-256","lagging":true,"listed":false,"status":"No available stats","testing":false},"Parallel-Scrypt":{"id":140,"tag":"DUO","algorithm":"Scrypt","lagging":true,"listed":false,"status":"No available stats","testing":false},"Earthcoin":{"id":19,"tag":"EAC","algorithm":"Scrypt","lagging":true,"listed":false,"status":"No market","testing":false},"EtherGem":{"id":307,"tag":"EGEM","algorithm":"Ethash","lagging":false,"listed":true,"status":"Active","testing":false},"Ellaism":{"id":221,"tag":"ELLA","algorithm":"Ethash","lagging":false,"listed":true,"status":"Active","testing":false},"Elliot":{"id":251,"tag":"ELLI","algorithm":"Xevan","lagging":false,"listed":false,"status":"PoW phase over","testing":false},"Einsteinium":{"id":15,"tag":"EMC2","algorithm":"Scrypt","lagging":false,"listed":true,"status":"Active","testing":false},"Entropycoin":{"id":79,"tag":"ENC","algorithm":"Scrypt-N","lagging":true,"listed":false,"status":"No market","testing":false},"Experiencecoin":{"id":136,"tag":"EPC","algorithm":"Scrypt","lagging":true,"listed":false,"status":"Inactive","testing":false},"EtherSocial":{"id":320,"tag":"ESN","algorithm":"Ethash","lagging":false,"listed":true,"status":"Active","testing":false},"EthereumClassic":{"id":162,"tag":"ETC","algorithm":"Etchash","lagging":false,"listed":true,"status":"Active","testing":false},"Ethereum":{"id":151,"tag":"ETH","algorithm":"Ethash","lagging":false,"listed":true,"status":"Active","testing":false},"Ether-1":{"id":306,"tag":"ETHO","algorithm":"Ethash","lagging":false,"listed":true,"status":"Active","testing":false},"Electroneum":{"id":213,"tag":"ETN","algorithm":"CryptoNight","lagging":false,"listed":false,"status":"PoW phase over","testing":false},"Electronero":{"id":284,"tag":"ETNX","algorithm":"CryptoNightFast","lagging":true,"listed":false,"status":"Chain forked","testing":false},"Metaverse":{"id":209,"tag":"ETP","algorithm":"Ethash","lagging":false,"listed":true,"status":"Active","testing":false},"Euno":{"id":310,"tag":"EUNO","algorithm":"X11","lagging":true,"listed":true,"status":"PoW phase over","testing":false},"Execoin":{"id":20,"tag":"EXE","algorithm":"Scrypt-N","lagging":true,"listed":false,"status":"No available stats","testing":false},"Exosis":{"id":316,"tag":"EXO","algorithm":"X16R","lagging":true,"listed":false,"status":"Active","testing":false},"Expanse":{"id":154,"tag":"EXP","algorithm":"Ethash","lagging":false,"listed":true,"status":"Active","testing":false},"Fantomcoin":{"id":102,"tag":"FCN","algorithm":"CryptoNight","lagging":true,"listed":false,"status":"No market","testing":false},"Firo":{"id":175,"tag":"FIRO","algorithm":"MTP","lagging":false,"listed":true,"status":"Active","testing":false},"Folm":{"id":241,"tag":"FLM","algorithm":"PHI1612","lagging":true,"listed":false,"status":"No available stats","testing":false},"Florin":{"id":222,"tag":"FLO","algorithm":"Scrypt","lagging":false,"listed":true,"status":"Active","testing":false},"Fluttercoin":{"id":36,"tag":"FLT","algorithm":"Scrypt","lagging":true,"listed":false,"status":"No available stats","testing":false},"Freshcoin":{"id":118,"tag":"FRSH","algorithm":"Fresh","lagging":true,"listed":false,"status":"PoW phase over","testing":false},"Fastcoin":{"id":63,"tag":"FST","algorithm":"Scrypt","lagging":true,"listed":false,"status":"No available stats","testing":false},"Feathercoin":{"id":8,"tag":"FTC","algorithm":"NeoScrypt","lagging":false,"listed":true,"status":"Active","testing":false},"GameCredits":{"id":147,"tag":"GAME","algorithm":"Scrypt","lagging":false,"listed":true,"status":"PoW phase over","testing":false},"Goldblocks":{"id":160,"tag":"GB","algorithm":"X11","lagging":true,"listed":false,"status":"PoW phase over","testing":false},"GoByte":{"id":225,"tag":"GBX","algorithm":"NeoScrypt","lagging":false,"listed":true,"status":"Active","testing":false},"GDenomination":{"id":50,"tag":"GDN","algorithm":"X11","lagging":true,"listed":false,"status":"No market","testing":false},"Geocoin":{"id":135,"tag":"GEO","algorithm":"Qubit","lagging":false,"listed":false,"status":"PoW phase over","testing":false},"Gexan":{"id":308,"tag":"GEX","algorithm":"PHI2","lagging":true,"listed":false,"status":"Active","testing":false},"Gincoin":{"id":250,"tag":"GIN","algorithm":"X16RT","lagging":true,"listed":true,"status":"No available stats","testing":false},"Globalcoin":{"id":81,"tag":"GLC","algorithm":"Scrypt","lagging":true,"listed":false,"status":"No available stats","testing":false},"Goalcoin":{"id":87,"tag":"GOAL","algorithm":"Scrypt","lagging":true,"listed":false,"status":"No available stats","testing":false},"Graft":{"id":261,"tag":"GRFT","algorithm":"CNReverseWaltz","lagging":false,"listed":true,"status":"Active","testing":false},"Grimm":{"id":325,"tag":"GRIMM","algorithm":"Equihash (150,5)","lagging":true,"listed":false,"status":"No available stats","testing":false},"Grin-CT31":{"id":299,"tag":"GRIN","algorithm":"Cuckatoo31","lagging":false,"listed":false,"status":"PoW phase over","testing":false},"Grin-CR29":{"id":293,"tag":"GRIN","algorithm":"Cuckarooz29","lagging":false,"listed":false,"status":"PoW phase over","testing":false},"Grin-CT32":{"id":324,"tag":"GRIN","algorithm":"Cuckatoo32","lagging":false,"listed":true,"status":"Active","testing":false},"Garlicoin":{"id":243,"tag":"GRLC","algorithm":"Allium","lagging":false,"listed":false,"status":"Active","testing":false},"GroestlCoin":{"id":48,"tag":"GRS","algorithm":"Groestl","lagging":false,"listed":true,"status":"Active","testing":false},"Gravium":{"id":262,"tag":"GRV","algorithm":"X16R","lagging":true,"listed":false,"status":"No available stats","testing":false},"Gentarium":{"id":267,"tag":"GTM","algorithm":"Lyra2z","lagging":true,"listed":false,"status":"PoW phase over","testing":false},"Halcyon":{"id":122,"tag":"HAL","algorithm":"NeoScrypt","lagging":false,"listed":false,"status":"Active","testing":false},"Hanacoin":{"id":270,"tag":"HANA","algorithm":"Lyra2REv3","lagging":false,"listed":true,"status":"Active","testing":false},"Heldcoin":{"id":253,"tag":"HDLC","algorithm":"Scrypt","lagging":true,"listed":false,"status":"No available stats","testing":false},"Hirocoin":{"id":33,"tag":"HIRO","algorithm":"X11","lagging":true,"listed":false,"status":"Inactive","testing":false},"Hilux":{"id":295,"tag":"HLX","algorithm":"X16R","lagging":true,"listed":false,"status":"No available stats","testing":false},"Handshake":{"id":327,"tag":"HNS","algorithm":"Handshake","lagging":false,"listed":true,"status":"Active","testing":false},"HelpTheHomeless":{"id":258,"tag":"HTH","algorithm":"X25X","lagging":false,"listed":false,"status":"Active","testing":false},"Hush":{"id":168,"tag":"HUSH","algorithm":"Equihash","lagging":false,"listed":false,"status":"Active","testing":false},"Heavycoin":{"id":35,"tag":"HVC","algorithm":"Heavycoin","lagging":true,"listed":false,"status":"No market","testing":false},"Ivugeocoin":{"id":142,"tag":"IEC","algorithm":"Scrypt","lagging":true,"listed":false,"status":"Inactive","testing":false},"Imagecoin":{"id":311,"tag":"IMG","algorithm":"X11","lagging":true,"listed":false,"status":"Active","testing":false},"Influxcoin":{"id":149,"tag":"INFX","algorithm":"X11","lagging":false,"listed":false,"status":"Active","testing":false},"Innova":{"id":229,"tag":"INN","algorithm":"NeoScrypt","lagging":true,"listed":false,"status":"PoW phase over","testing":false},"Jackpotcoin":{"id":80,"tag":"JPC","algorithm":"JHA","lagging":true,"listed":false,"status":"No available stats","testing":false},"Karmacoin":{"id":38,"tag":"KARM","algorithm":"X11","lagging":true,"listed":false,"status":"No available stats","testing":false},"Kadena":{"id":334,"tag":"KDA","algorithm":"Kadena","lagging":false,"listed":true,"status":"Active","testing":false},"Komodo":{"id":174,"tag":"KMD","algorithm":"Equihash","lagging":false,"listed":true,"status":"Active","testing":false},"Krypton":{"id":163,"tag":"KR","algorithm":"Ethash","lagging":true,"listed":false,"status":"PoW phase over","testing":false},"Karbo":{"id":176,"tag":"KRB","algorithm":"CryptoNight","lagging":false,"listed":true,"status":"Active","testing":false},"LBRY":{"id":164,"tag":"LBC","algorithm":"LBRY","lagging":false,"listed":true,"status":"Active","testing":false},"LitecoinCash":{"id":231,"tag":"LCC","algorithm":"SHA-256","lagging":false,"listed":true,"status":"Active","testing":false},"LitecoinPlus":{"id":275,"tag":"LCP","algorithm":"Scrypt","lagging":false,"listed":false,"status":"Active","testing":false},"Logicoin":{"id":57,"tag":"LGC","algorithm":"X11","lagging":true,"listed":false,"status":"No market","testing":false},"Legendarycoin":{"id":68,"tag":"LGD","algorithm":"Scrypt","lagging":true,"listed":false,"status":"No market","testing":false},"LimecoinX":{"id":46,"tag":"LIMX","algorithm":"X11","lagging":true,"listed":false,"status":"No available stats","testing":false},"Linx":{"id":195,"tag":"LINX","algorithm":"Scrypt","lagging":true,"listed":false,"status":"No available stats","testing":false},"Loki":{"id":249,"tag":"LOKI","algorithm":"RandomXL","lagging":true,"listed":false,"status":"PoW phase over","testing":false},"Litecoin":{"id":4,"tag":"LTC","algorithm":"Scrypt","lagging":false,"listed":true,"status":"Active","testing":false},"LitecoinX":{"id":78,"tag":"LTCX","algorithm":"X11","lagging":true,"listed":false,"status":"No available stats","testing":false},"Lethean":{"id":296,"tag":"LTHN","algorithm":"CryptoNightR","lagging":false,"listed":true,"status":"Active","testing":false},"Luxcoin":{"id":212,"tag":"LUX","algorithm":"PHI2","lagging":false,"listed":true,"status":"Active","testing":false},"Magnet":{"id":237,"tag":"MAG","algorithm":"X11","lagging":false,"listed":false,"status":"PoW phase over","testing":false},"Mano":{"id":254,"tag":"MANO","algorithm":"Lyra2z","lagging":false,"listed":false,"status":"PoW phase over","testing":false},"Marucoin ":{"id":84,"tag":"MARU","algorithm":"X13","lagging":true,"listed":false,"status":"No market","testing":false},"Maxcoin":{"id":73,"tag":"MAX","algorithm":"Keccak","lagging":false,"listed":false,"status":"Active","testing":false},"Maza":{"id":70,"tag":"MAZA","algorithm":"SHA-256","lagging":true,"listed":false,"status":"No available stats","testing":false},"MCT+":{"id":257,"tag":"MCT","algorithm":"Lyra2z","lagging":true,"listed":false,"status":"PoW phase over","testing":false},"Megacoin":{"id":26,"tag":"MEC","algorithm":"Scrypt","lagging":true,"listed":false,"status":"No available stats","testing":false},"Kittehcoin":{"id":16,"tag":"MEOW","algorithm":"Scrypt","lagging":true,"listed":false,"status":"Inactive","testing":false},"Millionaire":{"id":91,"tag":"MIL","algorithm":"X11","lagging":true,"listed":false,"status":"PoW phase over","testing":false},"Mindcoin":{"id":155,"tag":"MND","algorithm":"X11","lagging":true,"listed":false,"status":"No available stats","testing":false},"Minex":{"id":265,"tag":"MNX","algorithm":"Mars","lagging":false,"listed":false,"status":"Active","testing":false},"Monacoin":{"id":148,"tag":"MONA","algorithm":"Lyra2REv2","lagging":false,"listed":true,"status":"Active","testing":false},"Mooncoin":{"id":119,"tag":"MOON","algorithm":"Scrypt","lagging":false,"listed":false,"status":"Active","testing":false},"microCoin":{"id":41,"tag":"MRC","algorithm":"Chacha (Nf14)","lagging":true,"listed":false,"status":"No market","testing":false},"Masari":{"id":273,"tag":"MSR","algorithm":"CryptoNightFastV2","lagging":false,"listed":true,"status":"Active","testing":false},"MonetaryUnit":{"id":143,"tag":"MUE","algorithm":"X11","lagging":false,"listed":false,"status":"PoW phase over","testing":false},"Muniti":{"id":47,"tag":"MUN","algorithm":"X11","lagging":true,"listed":false,"status":"No market","testing":false},"Musicoin":{"id":178,"tag":"MUSIC","algorithm":"Ethash","lagging":false,"listed":false,"status":"PoW phase over","testing":false},"MWC-CR29":{"id":322,"tag":"MWC","algorithm":"Cuckarood29","lagging":false,"listed":true,"status":"Active","testing":false},"MWC-CT31":{"id":323,"tag":"MWC","algorithm":"Cuckatoo31","lagging":false,"listed":true,"status":"Active","testing":false},"Nautiluscoin":{"id":82,"tag":"NAUT","algorithm":"Scrypt","lagging":true,"listed":false,"status":"PoW phase over","testing":false},"Nimiq":{"id":300,"tag":"NIM","algorithm":"Argon2d-NIM","lagging":false,"listed":true,"status":"Active","testing":false},"Nix":{"id":264,"tag":"NIX","algorithm":"Lyra2REv2","lagging":true,"listed":false,"status":"PoW phase over","testing":false},"Gulden":{"id":64,"tag":"NLG","algorithm":"Sigma","lagging":false,"listed":false,"status":"AlgoSwitch","testing":false},"Namecoin":{"id":55,"tag":"NMC","algorithm":"SHA-256","lagging":true,"listed":false,"status":"Inactive","testing":false},"Noblecoin":{"id":44,"tag":"NOBL","algorithm":"M7M","lagging":true,"listed":false,"status":"PoW phase over","testing":false},"DNotes":{"id":146,"tag":"NOTE","algorithm":"Scrypt","lagging":true,"listed":false,"status":"PoW phase over","testing":false},"Energi":{"id":282,"tag":"NRG","algorithm":"Energi","lagging":false,"listed":false,"status":"PoW phase over","testing":false},"Novacoin":{"id":30,"tag":"NVC","algorithm":"Scrypt","lagging":true,"listed":false,"status":"Inactive","testing":false},"Nexus":{"id":302,"tag":"NXS","algorithm":"NexusHash","lagging":false,"listed":false,"status":"Active","testing":false},"Nyancoin":{"id":17,"tag":"NYAN","algorithm":"Scrypt","lagging":true,"listed":false,"status":"No available stats","testing":false},"DeepOnion":{"id":216,"tag":"ONION","algorithm":"X13","lagging":false,"listed":false,"status":"Active","testing":false},"Onix":{"id":194,"tag":"ONX","algorithm":"X11","lagging":true,"listed":false,"status":"No available stats","testing":false},"Orbitcoin":{"id":72,"tag":"ORB","algorithm":"NeoScrypt","lagging":false,"listed":false,"status":"Active","testing":false},"Galactrum":{"id":233,"tag":"ORE","algorithm":"Lyra2REv2","lagging":false,"listed":false,"status":"PoW phase over","testing":false},"Paccoin":{"id":239,"tag":"PAC","algorithm":"X11","lagging":false,"listed":true,"status":"Pow phase over","testing":false},"Pascalcoin":{"id":172,"tag":"PASC","algorithm":"RandomHash","lagging":false,"listed":false,"status":"Active","testing":true},"PascalLite":{"id":177,"tag":"PASL","algorithm":"Pascal","lagging":true,"listed":false,"status":"No available stats","testing":false},"Pigeoncoin":{"id":246,"tag":"PGN","algorithm":"X21S","lagging":true,"listed":false,"status":"Active","testing":false},"Pengolincoin":{"id":332,"tag":"PGO","algorithm":"CryptoNightTurtle","lagging":true,"listed":false,"status":"PoW phase over","testing":false},"Pinkcoin":{"id":205,"tag":"PINK","algorithm":"Scrypt","lagging":true,"listed":false,"status":"No available stats","testing":false},"Pirl":{"id":211,"tag":"PIRL","algorithm":"Ethash","lagging":false,"listed":true,"status":"PoW phase over","testing":false},"Potcoin":{"id":18,"tag":"POT","algorithm":"Scrypt","lagging":true,"listed":false,"status":"PoW phase over","testing":false},"Peercoin":{"id":52,"tag":"PPC","algorithm":"SHA-256","lagging":false,"listed":true,"status":"Active","testing":false},"Phoenixcoin":{"id":71,"tag":"PXC","algorithm":"NeoScrypt","lagging":false,"listed":false,"status":"Active","testing":false},"Prime-XI":{"id":190,"tag":"PXI","algorithm":"X11","lagging":true,"listed":false,"status":"No available stats","testing":false},"Québecoin":{"id":45,"tag":"QBC","algorithm":"X11","lagging":true,"listed":false,"status":"No available stats","testing":false},"Quazarcoin":{"id":105,"tag":"QCN","algorithm":"CryptoNight","lagging":true,"listed":false,"status":"No market","testing":false},"QuarkChain":{"id":318,"tag":"QKC","algorithm":"Ethash","lagging":false,"listed":true,"status":"Active","testing":false},"Qyno":{"id":269,"tag":"QNO","algorithm":"NeoScrypt","lagging":false,"listed":false,"status":"PoW phase over","testing":false},"Quark":{"id":137,"tag":"QRK","algorithm":"Quark","lagging":true,"listed":false,"status":"No available stats","testing":false},"Quantum R L":{"id":263,"tag":"QRL","algorithm":"RandomX","lagging":false,"listed":true,"status":"Active","testing":false},"Rubycoin":{"id":95,"tag":"RBY","algorithm":"Scrypt","lagging":true,"listed":false,"status":"PoW phase over","testing":false},"Reddcoin":{"id":11,"tag":"RDD","algorithm":"Scrypt","lagging":true,"listed":false,"status":"PoW phase over","testing":false},"Ripoffcoin":{"id":108,"tag":"RIPO","algorithm":"Scrypt","lagging":true,"listed":false,"status":"No available stats","testing":false},"Rito":{"id":319,"tag":"RITO","algorithm":"X21S","lagging":false,"listed":false,"status":"Active","testing":false},"RonPaulCoin":{"id":58,"tag":"RPC","algorithm":"Scrypt","lagging":true,"listed":false,"status":"No available stats","testing":false},"Rupee":{"id":235,"tag":"RUP","algorithm":"Lyra2REv2","lagging":true,"listed":false,"status":"No market","testing":false},"Ravencoin":{"id":234,"tag":"RVN","algorithm":"KawPow","lagging":false,"listed":true,"status":"Active","testing":false},"Ryo":{"id":260,"tag":"RYO","algorithm":"CryptoNightGPU","lagging":false,"listed":true,"status":"Active","testing":false},"Razor":{"id":96,"tag":"RZR","algorithm":"Scrypt","lagging":true,"listed":false,"status":"No market","testing":false},"Saturn2coin":{"id":39,"tag":"SAT2","algorithm":"Scrypt","lagging":true,"listed":false,"status":"PoW phase over","testing":false},"Sia":{"id":161,"tag":"SC","algorithm":"Sia","lagging":false,"listed":true,"status":"Active","testing":false},"Scorecoin":{"id":181,"tag":"SCORE","algorithm":"Scrypt","lagging":true,"listed":false,"status":"No market","testing":false},"Seraph":{"id":247,"tag":"SERA","algorithm":"PHI1612","lagging":true,"listed":false,"status":"No available stats","testing":false},"Sero":{"id":328,"tag":"SERO","algorithm":"ProgPow","lagging":false,"listed":true,"status":"Active","testing":false},"Shift":{"id":156,"tag":"SHIFT","algorithm":"Ethash","lagging":true,"listed":false,"status":"PoW phase over","testing":false},"Sibcoin":{"id":169,"tag":"SIB","algorithm":"X11Gost","lagging":false,"listed":true,"status":"Active","testing":false},"Signatum":{"id":191,"tag":"SIGT","algorithm":"Skunkhash","lagging":false,"listed":false,"status":"PoW phase over","testing":false},"Sinovate":{"id":277,"tag":"SIN","algorithm":"X25X","lagging":false,"listed":true,"status":"Active","testing":false},"Skeincoin":{"id":244,"tag":"SKC","algorithm":"Skein","lagging":true,"listed":false,"status":"No available stats","testing":false},"Sterlingcoin":{"id":117,"tag":"SLG","algorithm":"X13","lagging":true,"listed":false,"status":"PoW phase over","testing":false},"SmartCash":{"id":197,"tag":"SMART","algorithm":"Keccak","lagging":true,"listed":true,"status":"Active","testing":false},"Smartcoin":{"id":159,"tag":"SMC","algorithm":"X11","lagging":true,"listed":false,"status":"No market","testing":false},"Soilcoin":{"id":189,"tag":"SOIL","algorithm":"Ethash","lagging":true,"listed":false,"status":"Inactive","testing":false},"Sono":{"id":204,"tag":"SONO","algorithm":"SonoA","lagging":true,"listed":false,"status":"Inactive","testing":false},"Spaincoin":{"id":12,"tag":"SPA","algorithm":"Scrypt-N","lagging":true,"listed":false,"status":"No available stats","testing":false},"Savecoin":{"id":77,"tag":"SPC","algorithm":"SHA-256","lagging":true,"listed":false,"status":"No available stats","testing":false},"Spider":{"id":303,"tag":"SPDR","algorithm":"PHI2","lagging":true,"listed":false,"status":"No available stats","testing":false},"SimpleBank":{"id":252,"tag":"SPLB","algorithm":"NeoScrypt","lagging":true,"listed":false,"status":"Inactive","testing":false},"Securecoin":{"id":139,"tag":"SRC","algorithm":"Quark","lagging":true,"listed":false,"status":"No market","testing":false},"Straks":{"id":240,"tag":"STAK","algorithm":"Lyra2REv2","lagging":false,"listed":false,"status":"Active","testing":false},"Startcoin":{"id":132,"tag":"START","algorithm":"X11","lagging":false,"listed":false,"status":"Active","testing":false},"Sumokoin":{"id":196,"tag":"SUMO","algorithm":"CryptoNightR","lagging":false,"listed":true,"status":"Active","testing":false},"Talkcoin":{"id":94,"tag":"TAC","algorithm":"NIST5","lagging":true,"listed":false,"status":"No market","testing":false},"Tent":{"id":288,"tag":"TENT","algorithm":"Zhash","lagging":false,"listed":true,"status":"Active","testing":false},"Fedoracoin":{"id":2,"tag":"TIPS","algorithm":"Scrypt","lagging":true,"listed":false,"status":"Inactive","testing":false},"Traid":{"id":274,"tag":"TRAID","algorithm":"NeoScrypt","lagging":true,"listed":false,"status":"No available stats","testing":false},"Turtlecoin":{"id":292,"tag":"TRTL","algorithm":"ChukwaV2","lagging":false,"listed":false,"status":"Active","testing":false},"BitTubeCash":{"id":256,"tag":"TUBE","algorithm":"CuckooCycle","lagging":false,"listed":true,"status":"Active","testing":false},"Trezarcoin":{"id":215,"tag":"TZC","algorithm":"NeoScrypt","lagging":false,"listed":false,"status":"Active","testing":false},"Ubiq":{"id":173,"tag":"UBQ","algorithm":"Ubqhash","lagging":false,"listed":true,"status":"Active","testing":false},"Unbreakable":{"id":83,"tag":"UNB","algorithm":"SHA-256","lagging":true,"listed":false,"status":"No available stats","testing":false},"Universal":{"id":223,"tag":"UNIT","algorithm":"SHA-256","lagging":true,"listed":false,"status":"No available stats","testing":false},"Unobtanium":{"id":54,"tag":"UNO","algorithm":"SHA-256","lagging":false,"listed":false,"status":"Active","testing":false},"eUtopium":{"id":106,"tag":"UPM","algorithm":"NIST5","lagging":true,"listed":false,"status":"No market","testing":false},"uPlexa":{"id":309,"tag":"UPX","algorithm":"CryptoNightUPX","lagging":false,"listed":false,"status":"Active","testing":false},"Urocoin":{"id":100,"tag":"URO","algorithm":"X11","lagging":true,"listed":false,"status":"No available stats","testing":false},"USDe":{"id":31,"tag":"USDE","algorithm":"Scrypt","lagging":true,"listed":false,"status":"No market","testing":false},"Ultracoin":{"id":3,"tag":"UTC","algorithm":"Chacha (Nf14)","lagging":true,"listed":false,"status":"No available stats","testing":false},"Vidulum":{"id":331,"tag":"VDL","algorithm":"EquihashZero","lagging":false,"listed":true,"status":"Active","testing":false},"Veil-RandomX":{"id":336,"tag":"VEIL","algorithm":"RandomX","lagging":false,"listed":false,"status":"Active","testing":true},"Veil-SHA":{"id":335,"tag":"VEIL","algorithm":"SHA-256","lagging":false,"listed":false,"status":"Active","testing":true},"Veil-ProgPow":{"id":286,"tag":"VEIL","algorithm":"ProgPow","lagging":false,"listed":true,"status":"Active","testing":false},"Veilcoin":{"id":98,"tag":"VEIL_old","algorithm":"X13","lagging":true,"listed":false,"status":"No available stats","testing":false},"Viacoin":{"id":107,"tag":"VIA","algorithm":"Scrypt","lagging":false,"listed":true,"status":"Active","testing":false},"Vivo":{"id":200,"tag":"VIVO","algorithm":"NeoScrypt","lagging":false,"listed":true,"status":"Active","testing":false},"VirtualMining":{"id":62,"tag":"VMC","algorithm":"Scrypt-N","lagging":true,"listed":false,"status":"No market","testing":false},"Verus":{"id":333,"tag":"VRSC","algorithm":"VerusHash","lagging":true,"listed":false,"status":"Active","testing":false},"Vertcoin":{"id":5,"tag":"VTC","algorithm":"Verthash","lagging":false,"listed":false,"status":"Active","testing":true},"Vertical":{"id":259,"tag":"VTL","algorithm":"LBK3","lagging":true,"listed":false,"status":"No available stats","testing":false},"Worldcoin":{"id":29,"tag":"WDC","algorithm":"Scrypt","lagging":false,"listed":false,"status":"Active","testing":false},"X11":{"id":69,"tag":"XC","algorithm":"X11","lagging":true,"listed":false,"status":"PoW phase over","testing":false},"Cryptonite":{"id":184,"tag":"XCN","algorithm":"M7","lagging":true,"listed":false,"status":"No available stats","testing":false},"DigitalNote":{"id":104,"tag":"XDN","algorithm":"Wish","lagging":true,"listed":false,"status":"AlgoSwitch","testing":false},"XDNA":{"id":266,"tag":"XDNA","algorithm":"Hex","lagging":false,"listed":true,"status":"PoW phase over","testing":false},"Honorcoin":{"id":109,"tag":"XHC","algorithm":"X13","lagging":true,"listed":false,"status":"No market","testing":false},"HavenProtocol":{"id":279,"tag":"XHV","algorithm":"CryptoNightHaven","lagging":false,"listed":true,"status":"Active","testing":false},"Scala":{"id":280,"tag":"XLA","algorithm":"CryptoNightDefyx","lagging":false,"listed":false,"status":"AlgoSwitch","testing":false},"Solaris":{"id":179,"tag":"XLR","algorithm":"Xevan","lagging":false,"listed":false,"status":"PoW phase over","testing":false},"Monoeci":{"id":203,"tag":"XMCC","algorithm":"X11","lagging":true,"listed":false,"status":"PoW phase over","testing":false},"Motion":{"id":248,"tag":"XMN","algorithm":"X16R","lagging":true,"listed":true,"status":"No available stats","testing":false},"MoneroOriginal":{"id":238,"tag":"XMO","algorithm":"CryptoNight","lagging":true,"listed":false,"status":"No available stats","testing":false},"Monero":{"id":101,"tag":"XMR","algorithm":"RandomX","lagging":false,"listed":true,"status":"Active","testing":false},"Myriad-Groestl":{"id":49,"tag":"XMY","algorithm":"Myr-Groestl","lagging":false,"listed":true,"status":"Active","testing":false},"Myriad-Scrypt":{"id":32,"tag":"XMY","algorithm":"Scrypt","lagging":false,"listed":true,"status":"Active","testing":false},"Myriad-SHA":{"id":56,"tag":"XMY","algorithm":"SHA-256","lagging":false,"listed":true,"status":"Active","testing":false},"Myriad-Yescrypt":{"id":66,"tag":"XMY","algorithm":"Yescrypt","lagging":false,"listed":false,"status":"Active","testing":false},"Myriad-Argon2d":{"id":67,"tag":"XMY","algorithm":"Argon2d","lagging":false,"listed":false,"status":"Active","testing":true},"Paycoin":{"id":121,"tag":"XPY","algorithm":"SHA-256","lagging":true,"listed":false,"status":"PoW phase over","testing":false},"xRhodium":{"id":317,"tag":"XRC","algorithm":"X13","lagging":false,"listed":false,"status":"Active","testing":false},"Vcash":{"id":130,"tag":"XVC","algorithm":"Blake (XVC)","lagging":true,"listed":false,"status":"No available stats","testing":false},"Verge-Groestl":{"id":218,"tag":"XVG","algorithm":"Myr-Groestl","lagging":false,"listed":true,"status":"Active","testing":false},"Verge-Lyra2REv2":{"id":217,"tag":"XVG","algorithm":"Lyra2REv2","lagging":false,"listed":true,"status":"Active","testing":false},"Verge-X17":{"id":219,"tag":"XVG","algorithm":"X17","lagging":false,"listed":false,"status":"Active","testing":false},"Verge-Scrypt":{"id":150,"tag":"XVG","algorithm":"Scrypt","lagging":false,"listed":true,"status":"Active","testing":false},"Verge-Blake (2s)":{"id":220,"tag":"XVG","algorithm":"Blake (2s)","lagging":false,"listed":false,"status":"Active","testing":false},"Swap":{"id":301,"tag":"XWP","algorithm":"Cuckaroo29s","lagging":false,"listed":true,"status":"Active","testing":false},"YACoin":{"id":42,"tag":"YAC","algorithm":"Chacha (Nf17)","lagging":true,"listed":false,"status":"No available stats","testing":false},"Zano":{"id":330,"tag":"ZANO","algorithm":"ProgPowZ","lagging":false,"listed":true,"status":"Active","testing":false},"Zclassic":{"id":167,"tag":"ZCL","algorithm":"EquihashZero","lagging":false,"listed":true,"status":"Active","testing":false},"Zcash":{"id":166,"tag":"ZEC","algorithm":"Equihash","lagging":false,"listed":true,"status":"Active","testing":false},"Zel":{"id":287,"tag":"ZEL","algorithm":"ZelHash","lagging":false,"listed":true,"status":"Active","testing":false},"Horizen":{"id":185,"tag":"ZEN","algorithm":"Equihash","lagging":false,"listed":true,"status":"Active","testing":false},"Zero":{"id":210,"tag":"ZER","algorithm":"EquihashZero","lagging":false,"listed":true,"status":"Active","testing":false},"Zetacoin":{"id":53,"tag":"ZET","algorithm":"SHA-256","lagging":false,"listed":false,"status":"Active","testing":false},"01coin":{"id":338,"tag":"ZOC","algorithm":"NeoScrypt","lagging":false,"listed":false,"status":"Active","testing":false}}}
